sample/__init__.py
sample/calcprimenumbers.py
calcprimenumbers-1.1.1.dist-info/LICENSE.txt
calcprimenumbers-1.1.1.dist-info/METADATA
calcprimenumbers-1.1.1.dist-info/WHEEL
calcprimenumbers-1.1.1.dist-info/top_level.txt
calcprimenumbers-1.1.1.dist-info/RECORD
