Metadata-Version: 2.1
Name: calcprimenumbers
Version: 1.1.1
Summary: package example
Author: alejandro velazco
License-File: LICENSE.txt
Requires-Dist: cffi (==1.15.1)
Requires-Dist: Jinja2 (==3.1.2)
Requires-Dist: MarkupSafe (==2.1.1)
Requires-Dist: pycparser (==2.21)
Requires-Dist: pytz (==2022.1)
Requires-Dist: pytz-deprecation-shim (==0.1.0.post0)
Requires-Dist: rpy2 (==3.5.2)
Requires-Dist: tzdata (==2022.1)
Requires-Dist: tzlocal (==4.2)
